goldfish_backend/__init__.py
goldfish_backend/py.typed
goldfish_backend/core/auth.py
goldfish_backend/core/database.py
goldfish_backend/models/__init__.py
goldfish_backend/models/entity_learning.py
goldfish_backend/models/note.py
goldfish_backend/models/person.py
goldfish_backend/models/project.py
goldfish_backend/models/relationships.py
goldfish_backend/models/schemas.py
goldfish_backend/models/source_file.py
goldfish_backend/models/suggested_entity.py
goldfish_backend/models/task.py
goldfish_backend/models/topic.py
goldfish_backend/models/user.py
goldfish_backend/services/entity_recognition.py
goldfish_backend/services/suggestion_service.py
goldfish_backend/services/user_service.py
goldfish_backend-0.1.5.dist-info/METADATA
goldfish_backend-0.1.5.dist-info/WHEEL
goldfish_backend-0.1.5.dist-info/licenses/LICENSE
goldfish_backend-0.1.5.dist-info/RECORD
