Metadata-Version: 2.4
Name: goldfish-backend
Version: 0.1.5
Summary: AI-First Personal Knowledge Management - Shared Backend
Project-URL: Homepage, https://github.com/linxichen/goldfish
Project-URL: Repository, https://github.com/linxichen/goldfish
Project-URL: Documentation, https://github.com/linxichen/goldfish/tree/main/goldfish-backend
Project-URL: Bug Reports, https://github.com/linxichen/goldfish/issues
Author: Goldfish Team
License: MIT License
License-File: LICENSE
Keywords: ai,backend,entities,knowledge,management,notes
Classifier: Development Status :: 3 - Alpha
Classifier: Intended Audience :: Developers
Classifier: License :: OSI Approved :: MIT License
Classifier: Operating System :: OS Independent
Classifier: Programming Language :: Python :: 3
Classifier: Programming Language :: Python :: 3.11
Classifier: Programming Language :: Python :: 3.12
Classifier: Topic :: Office/Business :: Scheduling
Classifier: Topic :: Scientific/Engineering :: Artificial Intelligence
Classifier: Topic :: Text Processing
Requires-Python: >=3.11
Requires-Dist: alembic>=1.16.2
Requires-Dist: passlib[bcrypt]>=1.7.4
Requires-Dist: pydantic[email]>=2.11.7
Requires-Dist: python-jose[cryptography]>=3.5.0
Requires-Dist: sqlmodel>=0.0.24
Provides-Extra: dev
Requires-Dist: black>=24.0.0; extra == 'dev'
Requires-Dist: faker>=37.4.0; extra == 'dev'
Requires-Dist: httpx>=0.27.0; extra == 'dev'
Requires-Dist: mypy>=1.8.0; extra == 'dev'
Requires-Dist: pytest-asyncio>=1.0.0; extra == 'dev'
Requires-Dist: pytest-cov>=6.2.1; extra == 'dev'
Requires-Dist: pytest>=8.4.1; extra == 'dev'
Requires-Dist: ruff>=0.6.0; extra == 'dev'
Requires-Dist: types-passlib>=1.7.7.20250602; extra == 'dev'
Requires-Dist: types-python-jose>=3.5.0.20250531; extra == 'dev'
